{
  "generated": "2026-02-15T14:33:00.132738+00:00",
  "owner": "yanivmizrachiy",
  "total": 0,
  "repos": [],
  "errors": [
    {
      "repo": "__LIST__",
      "error": "gh api failed: users/yanivmizrachiy/repos?per_page=100&page=1&sort=updated | {\r\n  \"message\": \"Bad credentials\",\r\n  \"documentation_url\": \"https://docs.github.com/rest\",\r\n  \"status\": \"401\"\r\n}gh: Bad credentials (HTTP 401)"
    }
  ],
  "turbo": {
    "ts": "2026-02-15T14:33:00.132163+00:00",
    "top_n": 20,
    "decisions_written": 0,
    "clone_ok": 0,
    "fail": 0,
    "skip_existing": 0,
    "move_lists_dir": "/home/runner/work/system-core/system-core/STATE/repo-move-lists/2026-02-15T14-33-00.132163+00-00",
    "audits_dir": "/home/runner/work/system-core/system-core/STATE/repo-audits/2026-02-15T14-33-00.132163+00-00",
    "apply_dir": "/home/runner/work/system-core/system-core/STATE/repo-apply-scripts/2026-02-15T14-33-00.132163+00-00"
  }
}